Workbook

Sheet Instructions
A1: MS Excel Practical Exam
A2: Total Questions: 30
A3: Difficulty Level: Medium
A4: Syllabus: Formulas, Logical Functions, Lookups, INDEX-MATCH, Pivot Tables & Charts, Data Analysis
A5: Attempt all questions using appropriate Excel tools/functions.

Sheet Sales_Data
A1: Order_ID | B1: Region | C1: Salesperson | D1: Product | E1: Quantity | F1: Unit_Price | G1: Sales_Date | H1: Total Sales | I1: GST % | J1: GST AMT | K1: Final AMT | M1: Region | N1: Total Sales | P1: Qauntity | R1: Sales_Date | S1: Month Name | U1: LEFT USE | V1: COUNTIFS USE | W1: ROUND
A2: 301 | B2: North | C2: Amit | D2: Laptop | E2: 2 | F2: 45000 | G2: 05-01-2025 | H2: =E2*F2 -> 90000 | I2: =VLOOKUP(D2,Product_Master!A1:C7,3,0) -> 18 | J2: =H2*I2% -> 16200 | K2: =SUM(H2,J2) -> 106200 | M2: North | N2: =SUMIF(B2:B7,M2,H2:H7) -> 150000 | P2: =IF(E2>3,"High","Low") -> Low | R2: 45662 | S2: =TEXT(R2,"mmm") -> Jan | U2: =LEFT(C2,2) -> Am | V2: =COUNTIFS(D2:D7,"laptop",B2:B7,"North") -> 1 | W2: =ROUND(F2,-3) -> 45000
A3: 302 | B3: South | C3: Riya | D3: Mobile | E3: 5 | F3: 15000 | G3: 07-01-2025 | H3: =E3*F3 -> 75000 | I3: =VLOOKUP(D3,Product_Master!A2:C8,3,0) -> 12 | J3: =H3*I3% -> 9000 | K3: =SUM(H3,J3) -> 84000 | M3: South | N3: =SUMIF(B3:B8,M3,H3:H8) -> 165000 | P3: =IF(E3>3,"High","Low") -> High | R3: 45664 | S3: =TEXT(R3,"mmm") -> Jan | U3: =LEFT(C3,2) -> Ri | V3: =COUNTIFS(D3:D8,"laptop",B3:B8,"North") -> 0 | W3: =ROUND(F3,-3) -> 15000
A4: 303 | B4: East | C4: Kunal | D4: Tablet | E4: 3 | F4: 18000 | G4: 10-01-2025 | H4: =E4*F4 -> 54000 | I4: =VLOOKUP(D4,Product_Master!A3:C9,3,0) -> 12 | J4: =H4*I4% -> 6480 | K4: =SUM(H4,J4) -> 60480 | M4: East | N4: =SUMIF(B4:B9,M4,H4:H9) -> 54000 | P4: =IF(E4>3,"High","Low") -> Low | R4: 45667 | S4: =TEXT(R4,"mmm") -> Jan | U4: =LEFT(C4,2) -> Ku | V4: =COUNTIFS(D4:D9,"laptop",B4:B9,"North") -> 0 | W4: =ROUND(F4,-3) -> 18000
A5: 304 | B5: West | C5: Neha | D5: Laptop | E5: 1 | F5: 45000 | G5: 12-01-2025 | H5: =E5*F5 -> 45000 | I5: =VLOOKUP(D5,Product_Master!A4:C10,3,0) -> 18 | J5: =H5*I5% -> 8100 | K5: =SUM(H5,J5) -> 53100 | M5: West | N5: =SUMIF(B5:B10,M5,H5:H10) -> 45000 | P5: =IF(E5>3,"High","Low") -> Low | R5: 45669 | S5: =TEXT(R5,"mmm") -> Jan | U5: =LEFT(C5,2) -> Ne | V5: =COUNTIFS(D5:D10,"laptop",B5:B10,"North") -> 0 | W5: =ROUND(F5,-3) -> 45000
A6: 305 | B6: North | C6: Amit | D6: Mobile | E6: 4 | F6: 15000 | G6: 15-01-2025 | H6: =E6*F6 -> 60000 | I6: =VLOOKUP(D6,Product_Master!A5:C11,3,0) -> 12 | J6: =H6*I6% -> 7200 | K6: =SUM(H6,J6) -> 67200 | P6: =IF(E6>3,"High","Low") -> High | R6: 45672 | S6: =TEXT(R6,"mmm") -> Jan | U6: =LEFT(C6,2) -> Am | V6: =COUNTIFS(D6:D11,"laptop",B6:B11,"North") -> 0 | W6: =ROUND(F6,-3) -> 15000
A7: 306 | B7: South | C7: Riya | D7: Laptop | E7: 2 | F7: 45000 | G7: 18-01-2025 | H7: =E7*F7 -> 90000 | I7: =VLOOKUP(D7,Product_Master!A6:C12,3,0) -> 18 | J7: =H7*I7% -> 16200 | K7: =SUM(H7,J7) -> 106200 | P7: =IF(E7>3,"High","Low") -> Low | R7: 45675 | S7: =TEXT(R7,"mmm") -> Jan | U7: =LEFT(C7,2) -> Ri | V7: =COUNTIFS(D7:D12,"laptop",B7:B12,"North") -> 0 | W7: =ROUND(F7,-3) -> 45000
A8: =COUNTA(A2:A7) -> 6 | K8: =SUM(K2:K7) -> 477180
J10: MAX AMT | K10: =MAX(K2:K7) -> 106200
J11: MIN AMT | K11: =MIN(K2:K7) -> 53100
B16: Product - Wise Total Sales | E16: Region-Wise Total Sales | H16: Pivot Chart | N16: DUPLICATES | P16: FILTER USE
N17: NO DUPLICATES | P17: {=_xlfn._xlws.FILTER(A2:A7,(D2:D7="Laptop")*(E2:E7>1))} -> 301
B18: Row Labels | C18: Sum of Total Sales | E18: Row Labels | F18: Sum of Total Sales | P18: 306
B19: Laptop | C19: 225000 | E19: East | F19: 54000
B20: Mobile | C20: 135000 | E20: North | F20: 150000
B21: Tablet | C21: 54000 | E21: South | F21: 165000
B22: Grand Total | C22: 414000 | E22: West | F22: 45000
E23: Grand Total | F23: 414000

Sheet Product_Master
A1: Product | B1: Category | C1: GST_% | E1: Index match
A2: Laptop | B2: Electronics | C2: 18 | D2: laptop | E2: =INDEX($B2:$B8,MATCH($D2,$A2:$A8,0)) -> Electronics
A3: Mobile | B3: Electronics | C3: 12 | D3: Mobile | E3: =INDEX($B3:$B9,MATCH($D3,$A3:$A9,0)) -> Electronics
A4: Tablet | B4: Electronics | C4: 12 | D4: Tablet | E4: =INDEX($B4:$B10,MATCH($D4,$A4:$A10,0)) -> Electronics
A5: Laptop | B5: Electronics | C5: 18 | D5: Laptop | E5: =INDEX($B5:$B11,MATCH($D5,$A5:$A11,0)) -> Electronics
A6: Mobile | B6: Electronics | C6: 12 | D6: Mobile | E6: =INDEX($B6:$B12,MATCH($D6,$A6:$A12,0)) -> Electronics
A7: Tablet | B7: Electronics | C7: 12 | D7: Tablet | E7: =INDEX($B7:$B13,MATCH($D7,$A7:$A13,0)) -> Electronics
A8: Laptop | B8: Electronics | C8: 18 | D8: Laptop | E8: =INDEX($B8:$B14,MATCH($D8,$A8:$A14,0)) -> Electronics

Sheet Student_Marks
A1: Student_ID | B1: Name | C1: Maths | D1: Statistics | E1: Excel | F1: Attendance_% | H1: Total marks | J1: ATTENDANCE | L1: Median stats marks | N1: SD of Excel Marks | P1: Concat Use
A2: 1 | B2: Rahul | C2: 78 | D2: 82 | E2: 85 | F2: 92 | H2: =SUM(C2:E2) -> 245 | I2: =IF(H2>=$H$7,"Topper","Below Topper") -> Topper | J2: =IF(F2>=85,"Eligible","Not Eligible") -> Eligible | L2: =MEDIAN(D2:D6) -> 82 | N2: =_xlfn.STDEV.S($E$2:$E$6) -> 14.737707 | P2: =_xlfn.CONCAT(A2,B2) -> 1Rahul
A3: 2 | B3: Sneha | C3: 88 | D3: 91 | E3: 90 | F3: 96 | H3: =SUM(C3:E3) -> 269 | I3: =IF(H3>=$H$7,"Topper","Below Topper") -> Topper | J3: =IF(F3>=85,"Eligible","Not Eligible") -> Eligible | L3: =MEDIAN(D3:D7) -> 79.5 | N3: =_xlfn.STDEV.S($E$2:$E$6) -> 14.737707 | P3: =_xlfn.CONCAT(A3,B3) -> 2Sneha
A4: 3 | B4: Arjun | C4: 65 | D4: 70 | E4: 72 | F4: 85 | H4: =SUM(C4:E4) -> 207 | I4: =IF(H4>=$H$7,"Topper","Below Topper") -> Below Topper | J4: =IF(F4>=85,"Eligible","Not Eligible") -> Eligible | L4: =MEDIAN(D4:D8) -> 70 | N4: =_xlfn.STDEV.S($E$2:$E$6) -> 14.737707 | P4: =_xlfn.CONCAT(A4,B4) -> 3Arjun
A5: 4 | B5: Pooja | C5: 92 | D5: 89 | E5: 94 | F5: 98 | H5: =SUM(C5:E5) -> 275 | I5: =IF(H5>=$H$7,"Topper","Below Topper") -> Topper | J5: =IF(F5>=85,"Eligible","Not Eligible") -> Eligible | L5: =MEDIAN(D5:D9) -> 74.5 | N5: =_xlfn.STDEV.S($E$2:$E$6) -> 14.737707 | P5: =_xlfn.CONCAT(A5,B5) -> 4Pooja
A6: 5 | B6: Vikas | C6: 55 | D6: 60 | E6: 58 | F6: 80 | H6: =SUM(C6:E6) -> 173 | I6: =IF(H6>=$H$7,"Topper","Below Topper") -> Below Topper | J6: =IF(F6>=85,"Eligible","Not Eligible") -> Not Eligible | L6: =MEDIAN(D6:D10) -> 60 | N6: =_xlfn.STDEV.S($E$2:$E$6) -> 14.737707 | P6: =_xlfn.CONCAT(A6,B6) -> 5Vikas
G7: AVG MARKS | H7: =AVERAGE(H2:H6) -> 233.8
E9: COUNT attendance | F9: =COUNTIF(F2:F6,">90") -> 3
B12: BAR CHART

Sheet Questions
A1: 1. Calculate Total Sales for each order (Quantity × Unit_Price). | J1: 2
A2: 2. Calculate GST Amount using VLOOKUP from Product_Master. | J2: 2
A3: 3. Find Final Amount payable (Total Sales + GST). | J3: 2
A4: 4. Find Grand Total of Final Amount. | J4: 2
A5: 5. Count total number of orders using COUNTA. | J5: 2
A6: 6. Find Region-wise total sales using SUMIF. | J6: 2
A7: 7. Use IF to classify Quantity as High (>3) or Low (<=3). | J7: 2
A8: 8. Find the maximum and minimum Final Amount. | J8: 2
A9: 9. Extract month name from Sales_Date. | J9: 2
A10: 10. Sort Sales_Data by Final Amount (Descending). | J10: 2
A11: 11. Use INDEX-MATCH to fetch Product Category. | J11: 2
A12: 12. Calculate average marks of each student. | J12: 2
... A30: 30. Protect the Student_Marks sheet. | J30: 2
J32: =SUM(J1:J30) -> 60
